pyttman_base_plugin/__init__.py
pyttman_plugin_base-1.0.9.dist-info/METADATA
pyttman_plugin_base-1.0.9.dist-info/WHEEL
pyttman_plugin_base-1.0.9.dist-info/top_level.txt
pyttman_plugin_base-1.0.9.dist-info/RECORD
